rust_ai_core_bindings/__init__.py
rust_ai_core_bindings/__init__.pyi
rust_ai_core_bindings/py.typed
rust_ai_core_bindings/rust_ai_core_bindings.cpython-311-x86_64-linux-gnu.so
rust_ai_core_bindings-0.2.7.dist-info/METADATA
rust_ai_core_bindings-0.2.7.dist-info/WHEEL
rust_ai_core_bindings-0.2.7.dist-info/licenses/LICENSE-MIT
rust_ai_core_bindings-0.2.7.dist-info/RECORD
