Metadata-Version: 2.4
Name: rust-ai-core-bindings
Version: 0.2.7
Classifier: Development Status :: 4 - Beta
Classifier: Intended Audience :: Developers
Classifier: Intended Audience :: Science/Research
Classifier: License :: OSI Approved :: MIT License
Classifier: Operating System :: OS Independent
Classifier: Programming Language :: Python :: 3
Classifier: Programming Language :: Python :: 3.9
Classifier: Programming Language :: Python :: 3.10
Classifier: Programming Language :: Python :: 3.11
Classifier: Programming Language :: Python :: 3.12
Classifier: Programming Language :: Python :: 3.13
Classifier: Programming Language :: Python :: 3.14
Classifier: Programming Language :: Rust
Classifier: Topic :: Scientific/Engineering :: Artificial Intelligence
Classifier: Topic :: Software Development :: Libraries :: Python Modules
Requires-Dist: numpy>=1.20
Requires-Dist: pytest>=7.0 ; extra == 'dev'
Requires-Dist: pytest-benchmark>=4.0 ; extra == 'dev'
Provides-Extra: dev
License-File: LICENSE-MIT
Summary: Python bindings for rust-ai-core: memory estimation, device detection, and ML utilities
Keywords: machine-learning,cuda,gpu,tensors,deep-learning,memory-estimation
Home-Page: https://github.com/tzervas/rust-ai-core
Author-email: Tyler Zervas <tz-dev@vectorweight.com>
License: MIT
Requires-Python: >=3.9
Project-URL: Documentation, https://docs.rs/rust-ai-core
Project-URL: Homepage, https://github.com/tzervas/rust-ai-core
Project-URL: Issues, https://github.com/tzervas/rust-ai-core/issues
Project-URL: Repository, https://github.com/tzervas/rust-ai-core
